README.md
pyproject.toml
setup.py
management/__init__.py
management/cli.py
management/cluster_ops.py
management/compute_node_ops.py
management/constants.py
management/kv_store.py
management/mgmt_node_ops.py
management/pci_utils.py
management/rpc_client.py
management/shell_utils.py
management/storage_node_ops.py
management/utils.py
management/controllers/__init__.py
management/controllers/cluster_events.py
management/controllers/cluster_lifecycle.py
management/controllers/device_lifecycle.py
management/controllers/events_controller.py
management/controllers/lvol_controller.py
management/controllers/mgmt_events.py
management/controllers/node_lifecycle.py
management/controllers/pool_controller.py
management/controllers/snapshot_controller.py
management/controllers/storage_events.py
management/models/__init__.py
management/models/base_model.py
management/models/cluster.py
management/models/compute_node.py
management/models/device_stat.py
management/models/events.py
management/models/global_settings.py
management/models/iface.py
management/models/mgmt_node.py
management/models/nvme_device.py
management/models/pool.py
management/models/snapshot.py
management/models/storage_node.py
management/scripts/__init__.py
management/scripts/db_config_double.sh
management/scripts/db_config_single.sh
management/scripts/deploy_stack.sh
management/scripts/docker-compose-swarm.yml
management/scripts/haproxy.cfg
management/scripts/install_deps.sh
management/scripts/set_db_config.sh
management/services/__init__.py
management/services/device_monitor.py
management/services/device_stat_collector.py
management/services/install_service.sh
management/services/lvol_stat_collector.py
management/services/mgmt_node_monitor.py
management/services/node_monitor.py
management/services/port_stat_collector.py
management/services/remove_service.sh
management/services/service_template.service
management/services/stat_collector.py
management/spdk_installer/__init__.py
simplybk_dev.egg-info/PKG-INFO
simplybk_dev.egg-info/SOURCES.txt
simplybk_dev.egg-info/dependency_links.txt
simplybk_dev.egg-info/entry_points.txt
simplybk_dev.egg-info/requires.txt
simplybk_dev.egg-info/top_level.txt