Metadata-Version: 2.1
Name: simplybk-dev
Version: 2.1.4
Summary: CLI for managing SimplyBlock cluster
Home-page: https://github.com/
Author: Hamdy Khader
Author-email: hamdy.khader@gmail.com
